{
  "indexes": [
    {
      "collectionGroup": "clients",
      "queryScope": "COLLECTION",
      "fields": [
        { "fieldPath": "assignedEmployeeId", "order": "ASCENDING" },
        { "fieldPath": "createdAt", "order": "DESCENDING" }
      ]
    },
    {
      "collectionGroup": "followups",
      "queryScope": "COLLECTION",
      "fields": [
        { "fieldPath": "assignedEmployeeId", "order": "ASCENDING" },
        { "fieldPath": "date", "order": "DESCENDING" }
      ]
    },
    {
      "collectionGroup": "tasks",
      "queryScope": "COLLECTION",
      "fields": [
        { "fieldPath": "assignedTo", "order": "ASCENDING" },
        { "fieldPath": "dueDate", "order": "ASCENDING" }
      ]
    },
    {
      "collectionGroup": "sales",
      "queryScope": "COLLECTION",
      "fields": [
        { "fieldPath": "assignedEmployeeId", "order": "ASCENDING" },
        { "fieldPath": "saleDate", "order": "DESCENDING" }
      ]
    },
    {
      "collectionGroup": "notifications",
      "queryScope": "COLLECTION",
      "fields": [
        { "fieldPath": "userId", "order": "ASCENDING" },
        { "fieldPath": "createdAt", "order": "DESCENDING" }
      ]
    },
    {
      "collectionGroup": "auditLogs",
      "queryScope": "COLLECTION",
      "fields": [
        { "fieldPath": "userId", "order": "ASCENDING" },
        { "fieldPath": "createdAt", "order": "DESCENDING" }
      ]
    }
  ],
  "fieldOverrides": []
}
